ds_connector_restapi/__init__.py
ds_connector_restapi/api/__init__.py
ds_connector_restapi/api/default_api.py
ds_connector_restapi/api/items_api.py
ds_connector_restapi/api_client.py
ds_connector_restapi/api_response.py
ds_connector_restapi/configuration.py
ds_connector_restapi/exceptions.py
ds_connector_restapi/models/__init__.py
ds_connector_restapi/models/example_response.py
ds_connector_restapi/models/http_validation_error.py
ds_connector_restapi/models/item.py
ds_connector_restapi/models/validation_error.py
ds_connector_restapi/models/validation_error_loc_inner.py
ds_connector_restapi/py.typed
ds_connector_restapi/rest.py
ds_connector_restapi-0.1.1.dist-info/LICENSE
ds_connector_restapi-0.1.1.dist-info/METADATA
ds_connector_restapi-0.1.1.dist-info/WHEEL
ds_connector_restapi-0.1.1.dist-info/RECORD
